scsc/__init__.py
scsc/graph/__init__.py
scsc/graph/call_graph.py
scsc/supply_chain.py
scsc/traces/__init__.py
scsc/traces/trace_collector.py
scsc/utils/__init__.py
scsc/utils/eth_utils.py
scsc-0.1.5.dist-info/LICENSE
scsc-0.1.5.dist-info/METADATA
scsc-0.1.5.dist-info/WHEEL
scsc-0.1.5.dist-info/entry_points.txt
scsc-0.1.5.dist-info/RECORD
