Metadata-Version: 2.3
Name: scsc
Version: 0.1.5
Summary: 
License: MIT
Author: Monica Jin
Author-email: monicachenjin@gmail.com
Requires-Python: >=3.12,<4
Classifier: License :: OSI Approved :: MIT License
Classifier: Programming Language :: Python :: 3
Classifier: Programming Language :: Python :: 3.12
Classifier: Programming Language :: Python :: 3.13
Requires-Dist: click (>=8.1.8,<9.0.0)
Requires-Dist: dash (>=2.18.2,<3.0.0)
Requires-Dist: dash-cytoscape (>=1.0.2,<2.0.0)
Requires-Dist: eth-utils (>=5.2.0,<6.0.0)
Requires-Dist: jinja2 (>=3.1.6,<4.0.0)
Requires-Dist: networkx (>=3.4.2,<4.0.0)
Requires-Dist: pydot (>=3.0.4,<4.0.0)
Requires-Dist: web3[tester] (>=7.8.0,<8.0.0)
